batch_sen2cor/__init__.py
batch_sen2cor/processing/__init__.py
batch_sen2cor/processing/batch_sen2cor.py
batch_sen2cor-0.0.3.dist-info/METADATA
batch_sen2cor-0.0.3.dist-info/WHEEL
batch_sen2cor-0.0.3.dist-info/top_level.txt
batch_sen2cor-0.0.3.dist-info/RECORD
