Metadata-Version: 2.1
Name: batch-sen2cor
Version: 0.0.3
Summary: Batch sen2cor for sentinel2 images.
Home-page: https://github.com/mtmiran/batch_sen2cor
Author: Mateus
License: UNKNOWN
Platform: UNKNOWN
Requires-Python: >=3.5
